lightcnn/__init__.py
lightcnn/model.py
lightcnn/preprocessing.py
lightcnn/weights/LightCNN-V4_checkpoint.pth.tar
lightcnn-0.2.0.dist-info/LICENSE
lightcnn-0.2.0.dist-info/METADATA
lightcnn-0.2.0.dist-info/WHEEL
lightcnn-0.2.0.dist-info/top_level.txt
lightcnn-0.2.0.dist-info/RECORD
